maka/__init__.py
maka/monitor.py
maka-0.0.3.dist-info/LICENSE
maka-0.0.3.dist-info/METADATA
maka-0.0.3.dist-info/WHEEL
maka-0.0.3.dist-info/top_level.txt
maka-0.0.3.dist-info/RECORD
