Metadata-Version: 2.1
Name: maka
Version: 0.0.3
Summary: MAKA Python for online script monitoring and control.
Home-page: https://github.com/JamesRunnalls/river-trace
Author: James Runnalls
Author-email: <runnalls.james@gmail.com>
License: GNU GENERAL PUBLIC LICENSE
Keywords: python,MAKA,monitoring,monitor
Platform: UNKNOWN
License-File: LICENSE
